smartobrowser/__init__.py
smartobrowser/browser.py
smartobrowser/cache.py
smartobrowser/compat.py
smartobrowser/exceptions.py
smartobrowser/helpers.py
smartobrowser/ordereddict.py
smartobrowser/responses.py
smartobrowser/forms/__init__.py
smartobrowser/forms/fields.py
smartobrowser/forms/form.py
smartobrowser-0.5.7.dist-info/LICENSE
smartobrowser-0.5.7.dist-info/METADATA
smartobrowser-0.5.7.dist-info/NOTICE
smartobrowser-0.5.7.dist-info/WHEEL
smartobrowser-0.5.7.dist-info/top_level.txt
smartobrowser-0.5.7.dist-info/RECORD
