Metadata-Version: 2.1
Name: smartobrowser
Version: 0.5.7
Summary: Your friendly neighborhood web scraper
Home-page: https://github.com/jmcarp/robobrowser
Author: Hamza Khurshid
Author-email: hamzakhurshid97@gmail.com
License: MIT
Keywords: smartobrowser
Platform: UNKNOWN
Classifier: Development Status :: 2 - Pre-Alpha
Classifier: Intended Audience :: Developers
Classifier: License :: OSI Approved :: BSD License
Classifier: Natural Language :: English
Classifier: Programming Language :: Python :: 2
Classifier: Programming Language :: Python :: 2.6
Classifier: Programming Language :: Python :: 2.7
Classifier: Programming Language :: Python :: 3
Classifier: Programming Language :: Python :: 3.3
Classifier: Programming Language :: Python :: 3.4
Requires-Dist: beautifulsoup4 (>=4.3.2)
Requires-Dist: requests (>=2.6.0)
Requires-Dist: six (>=1.9.0)
Requires-Dist: Werkzeug (>=0.10.4)
